YifyAPI/__init__.py
YifyAPI/yify.py
YifyAPI-0.6.5.dist-info/LICENSE
YifyAPI-0.6.5.dist-info/METADATA
YifyAPI-0.6.5.dist-info/WHEEL
YifyAPI-0.6.5.dist-info/top_level.txt
YifyAPI-0.6.5.dist-info/RECORD
