Metadata-Version: 2.1
Name: YifyAPI
Version: 0.6.5
Summary: A scraping API for Yify.
Home-page: https://github.com/ArjixGamer/YifyAPI
Author: ArjixGamer
Author-email: arjixg53@gmail.com
License: UNKNOWN
Keywords: movies,yify,torrents,download,hd
Platform: UNKNOWN
Classifier: Programming Language :: Python :: 3
Classifier: License :: OSI Approved :: MIT License
Classifier: Operating System :: OS Independent
Requires-Python: >=3.6
Requires-Dist: beautifulsoup4 (>=4.6.0)
Requires-Dist: requests (>=2.18.4)
